flask_htpasswd.py
flask_htpasswd-0.5.0.dist-info/LICENSE
flask_htpasswd-0.5.0.dist-info/METADATA
flask_htpasswd-0.5.0.dist-info/WHEEL
flask_htpasswd-0.5.0.dist-info/top_level.txt
flask_htpasswd-0.5.0.dist-info/RECORD
