Metadata-Version: 2.1
Name: flask-htpasswd
Version: 0.5.0
Summary: Basic authentication support via htpasswd files in flask applications
Home-page: http://github.com/carsongee/flask-htpasswd
Author: Carson Gee
Author-email: x@carsongee.com
License: BSD New
Platform: any
Classifier: Environment :: Web Environment
Classifier: Intended Audience :: Developers
Classifier: License :: OSI Approved :: BSD License
Classifier: Operating System :: OS Independent
Classifier: Programming Language :: Python
Classifier: Topic :: Internet :: WWW/HTTP :: Dynamic Content
Classifier: Topic :: Software Development :: Libraries :: Python Modules
Classifier: Programming Language :: Python :: 2.7
Classifier: Programming Language :: Python :: 3
Classifier: Framework :: Flask
Requires-Python: >=3.5
Requires-Dist: Flask
Requires-Dist: passlib
Requires-Dist: pyjwt
Requires-Dist: tox
